odoo/addons/mail_full_expand/README.rst
odoo/addons/mail_full_expand/__init__.py
odoo/addons/mail_full_expand/__manifest__.py
odoo/addons/mail_full_expand/i18n/ca.po
odoo/addons/mail_full_expand/i18n/de.po
odoo/addons/mail_full_expand/i18n/es.po
odoo/addons/mail_full_expand/i18n/es_CO.po
odoo/addons/mail_full_expand/i18n/fr.po
odoo/addons/mail_full_expand/i18n/hr.po
odoo/addons/mail_full_expand/i18n/it.po
odoo/addons/mail_full_expand/i18n/mail_full_expand.pot
odoo/addons/mail_full_expand/i18n/nb.po
odoo/addons/mail_full_expand/i18n/nl.po
odoo/addons/mail_full_expand/i18n/nl_NL.po
odoo/addons/mail_full_expand/i18n/pt.po
odoo/addons/mail_full_expand/i18n/pt_BR.po
odoo/addons/mail_full_expand/i18n/sl.po
odoo/addons/mail_full_expand/i18n/tr.po
odoo/addons/mail_full_expand/i18n/tr_TR.po
odoo/addons/mail_full_expand/readme/CONTRIBUTORS.rst
odoo/addons/mail_full_expand/readme/DESCRIPTION.rst
odoo/addons/mail_full_expand/readme/USAGE.rst
odoo/addons/mail_full_expand/static/description/icon.png
odoo/addons/mail_full_expand/static/description/index.html
odoo/addons/mail_full_expand/static/src/js/mail_full_expand.js
odoo/addons/mail_full_expand/static/src/scss/mail_full_expand.scss
odoo/addons/mail_full_expand/static/src/xml/mail_full_expand.xml
odoo/addons/mail_full_expand/views/assets.xml
odoo/addons/mail_full_expand/views/mail_full_expand.xml
odoo13_addon_mail_full_expand-13.0.1.0.1.dev5.dist-info/METADATA
odoo13_addon_mail_full_expand-13.0.1.0.1.dev5.dist-info/WHEEL
odoo13_addon_mail_full_expand-13.0.1.0.1.dev5.dist-info/top_level.txt
odoo13_addon_mail_full_expand-13.0.1.0.1.dev5.dist-info/RECORD
